{
  "properties": {
    "displayName": "Backup - Azure Virtual Desktop Session Host",
    "policyType": "Custom",
    "mode": "Indexed",
    "description": "Azure Backup for Virtual Machines tagged for backup in 'Digital - Azure Virtual Desktops' subscriptions",
    "metadata": {
      "version": "1.0.0",
      "category": "Backup"
    },
    "version": "1.0.0",
    "parameters": {
  "vaultLocation": {
    "type": "String",
    "metadata": {
      "displayName": "Vault Location",
      "description": "Azure region containing the VM and Recovery Services Vault",
      "strongType": "location"
    }
  },
  "backupPolicyId": {
    "type": "String",
    "metadata": {
      "displayName": "Backup Policy ID",
      "description": "Recovery Services Vault Azure VM backup policy",
      "strongType": "Microsoft.RecoveryServices/vaults/backupPolicies"
    }
  },
  "effect": {
    "type": "String",
    "defaultValue": "DeployIfNotExists",
    "allowedValues": [
      "DeployIfNotExists",
      "AuditIfNotExists",
      "Disabled"
    ]
  }
},
    "policyRule": {
      "if":   {
        "if": {
  "allOf": [
    {
      "field": "type",
      "equals": "Microsoft.Compute/virtualMachines"
    },
    {
      "field": "location",
      "equals": "[parameters('vaultLocation')]"
    },
    {
      "field": "tags['BackupPlan']",
      "equals": "Azure-AVD-DAILY-30D"
    }
  ]
}
      },
      "then": {
        "effect": "[parameters('effect')]",
        "details": {
          "roleDefinitionIds": [
            "/providers/microsoft.authorization/roleDefinitions/9980e02c-c2be-4d73-94e8-173b1dc7cf3c",
            "/providers/microsoft.authorization/roleDefinitions/5e467623-bb1f-42f4-a55d-6e525e11384b"
          ],
          "type": "Microsoft.RecoveryServices/backupprotecteditems",
          "deployment": {
            "properties": {
              "mode": "incremental",
              "template": {
                "$schema": "http://schema.management.azure.com/schemas/2015-01-01/deploymentTemplate.json#",
                "contentVersion": "1.0.0.0",
                "parameters": {
                  "backupPolicyId": {
                    "type": "String"
                  },
                  "fabricName": {
                    "type": "String"
                  },
                  "protectionContainers": {
                    "type": "String"
                  },
                  "protectedItems": {
                    "type": "String"
                  },
                  "sourceResourceId": {
                    "type": "String"
                  }
                },
                "resources": [
                  {
                    "apiVersion": "2017-05-10",
                    "name": "[concat('DeployProtection-',uniqueString(parameters('protectedItems')))]",
                    "type": "Microsoft.Resources/deployments",
                    "resourceGroup": "[first(skip(split(parameters('backupPolicyId'), '/'), 4))]",
                    "subscriptionId": "[first(skip(split(parameters('backupPolicyId'), '/'), 2))]",
                    "properties": {
                      "mode": "Incremental",
                      "template": {
                        "$schema": "https://schema.management.azure.com/schemas/2015-01-01/deploymentTemplate.json#",
                        "contentVersion": "1.0.0.0",
                        "parameters": {
                          "backupPolicyId": {
                            "type": "String"
                          },
                          "fabricName": {
                            "type": "String"
                          },
                          "protectionContainers": {
                            "type": "String"
                          },
                          "protectedItems": {
                            "type": "String"
                          },
                          "sourceResourceId": {
                            "type": "String"
                          }
                        },
                        "resources": [
                          {
                            "type": "Microsoft.RecoveryServices/vaults/backupFabrics/protectionContainers/protectedItems",
                            "name": "[concat(first(skip(split(parameters('backupPolicyId'), '/'), 8)), '/', parameters('fabricName'), '/',parameters('protectionContainers'), '/', parameters('protectedItems'))]",
                            "apiVersion": "2016-06-01",
                            "properties": {
                              "protectedItemType": "Microsoft.Compute/virtualMachines",
                              "policyId": "[parameters('backupPolicyId')]",
                              "sourceResourceId": "[parameters('sourceResourceId')]"
                            }
                          }
                        ]
                      },
                      "parameters": {
                        "backupPolicyId": {
                          "value": "[parameters('backupPolicyId')]"
                        },
                        "fabricName": {
                          "value": "[parameters('fabricName')]"
                        },
                        "protectionContainers": {
                          "value": "[parameters('protectionContainers')]"
                        },
                        "protectedItems": {
                          "value": "[parameters('protectedItems')]"
                        },
                        "sourceResourceId": {
                          "value": "[parameters('sourceResourceId')]"
                        }
                      }
                    }
                  }
                ]
              },
              "parameters": {
                "backupPolicyId": {
                  "value": "[parameters('backupPolicyId')]"
                },
                "fabricName": {
                  "value": "Azure"
                },
                "protectionContainers": {
                  "value": "[concat('iaasvmcontainer;iaasvmcontainerv2;', resourceGroup().name, ';' ,field('name'))]"
                },
                "protectedItems": {
                  "value": "[concat('vm;iaasvmcontainerv2;', resourceGroup().name, ';' ,field('name'))]"
                },
                "sourceResourceId": {
                  "value": "[concat('/subscriptions/', subscription().subscriptionId, '/resourceGroups/', resourceGroup().name, '/providers/Microsoft.Compute/virtualMachines/',field('name'))]"
                }
              }
            }
          }
        }
      }
    }
  },
  "id": "/providers/Microsoft.Authorization/policyDefinitions/345fa903-145c-4fe1-8bcd-93ec2adccde8/versions/9.5.0",
  "type": "Microsoft.Authorization/policyDefinitions/versions",
  "name": "9.5.0"
}